aquacalc/__init__.py
aquacalc/all_formulas.py
aquacalc/all_simple.py
aquacalc/aquacalc.py
test/__init__.py
test/testcodes.py
aquacalc-0.0.10.dist-info/METADATA
aquacalc-0.0.10.dist-info/WHEEL
aquacalc-0.0.10.dist-info/top_level.txt
aquacalc-0.0.10.dist-info/RECORD
