Metadata-Version: 2.1
Name: aquacalc
Version: 0.0.10
Summary: A package for water and sanitation calculations
Author: Bhuwan Panday
Author-email: bhuwanpanday1@gmail.com
